localstore/__init__.py
localstore/Dataset.py
localstore/DatasetConverter.py
localstore/LocalAPI.py
localstore/LocalStore.py
localstore-0.2.1.dist-info/LICENSE
localstore-0.2.1.dist-info/METADATA
localstore-0.2.1.dist-info/WHEEL
localstore-0.2.1.dist-info/RECORD
