Metadata-Version: 2.1
Name: localstore
Version: 0.2.1
Summary: LocalStore is a Python library that provides various operations on a local database of products, which can be used to store and manage information about items in a local store inventory and it also give mobility to create an local API for the database. Besides this it can convert CSV file to json.
Home-page: https://github.com/colddsam/LocalStore.git
License: MIT
Keywords: Data Conversion,Dataset Creation,CSV File Processing,JSON Serialization,Directory Traversal,File Reading,Data Cleaning,Hashing,Data Structure Manipulation,Exception Handling,File Writing
Author: colddsam
Author-email: dassamratkumar772@gmail.com
Requires-Python: >=3.10,<4.0
Classifier: License :: OSI Approved :: MIT License
Classifier: Programming Language :: Python :: 3
Classifier: Programming Language :: Python :: 3.10
Classifier: Programming Language :: Python :: 3.11
Classifier: Programming Language :: Python :: 3.12
Requires-Dist: fastapi (>=0.109.0,<0.110.0)
Requires-Dist: pandas (>=2.2.0,<3.0.0)
Requires-Dist: pydantic (>=2.5.3,<3.0.0)
Requires-Dist: uvicorn (>=0.26.0,<0.27.0)
Project-URL: Repository, https://github.com/colddsam/LocalStore.git
